zed_assistant/__init__.py
zed_assistant/cli.py
zed_assistant/model/__init__.py
zed_assistant/model/command_prompt/__init__.py
zed_assistant/model/command_prompt/defs.py
zed_assistant/model/command_prompt/prompt_runner.py
zed_assistant/model/command_prompt/template_system.j2
zed_assistant/model/defs.py
zed_assistant/settings/__init__.py
zed_assistant/settings/defs.py
zed_assistant/settings/loader.py
zed_assistant/utils/__init__.py
zed_assistant/utils/console.py
zed_assistant/utils/file_utils.py
zed_assistant/zed.py
zed_assistant-0.0.4.dist-info/LICENSE
zed_assistant-0.0.4.dist-info/METADATA
zed_assistant-0.0.4.dist-info/WHEEL
zed_assistant-0.0.4.dist-info/entry_points.txt
zed_assistant-0.0.4.dist-info/RECORD
