Metadata-Version: 2.1
Name: zed-assistant
Version: 0.0.4
Summary: Zed is an LLM-based CLI assistant built with python and Chat GPT
Home-page: https://github.com/hoffmannmatheus/zed
License: MIT
Author: Matheus Hoffmann Silva
Author-email: me@mhsilva.com
Requires-Python: >=3.8,<4.0
Classifier: License :: OSI Approved :: MIT License
Classifier: Programming Language :: Python :: 3
Classifier: Programming Language :: Python :: 3.8
Classifier: Programming Language :: Python :: 3.9
Classifier: Programming Language :: Python :: 3.10
Classifier: Programming Language :: Python :: 3.11
Requires-Dist: colorama (>=0.4.6,<0.5.0)
Requires-Dist: halo (>=0.0.31,<0.0.32)
Requires-Dist: jinja2 (>=3.1.3,<4.0.0)
Requires-Dist: openai (>=1.23.6,<2.0.0)
Project-URL: Repository, https://github.com/hoffmannmatheus/zed
